jsonn/jsonn.py
jsonn-0.0.8.dist-info/LICENCE
jsonn-0.0.8.dist-info/METADATA
jsonn-0.0.8.dist-info/WHEEL
jsonn-0.0.8.dist-info/top_level.txt
jsonn-0.0.8.dist-info/RECORD
