Metadata-Version: 2.1
Name: jsonn
Version: 0.0.8
Summary: A package for process large json files
Home-page: https://github.com/jjsman/jsonn/
Author: Jaroslaw Szkola
Author-email: jjsman@gmail.com
License: UNKNOWN
Platform: UNKNOWN
Classifier: Programming Language :: Python :: 3.6
Classifier: License :: OSI Approved :: GNU General Public License v3 (GPLv3)
Classifier: Operating System :: OS Independent
Requires-Dist: numpy (>=1.14.5)
Requires-Dist: pandas (==0.25)
Requires-Dist: chardet (>=4.0.0)
